sisu/__init__.py
sisu/embedding_idf.py
sisu/sisu.py
sisu/summarizer.py
sisu/datasets/__init__.py
sisu/datasets/covid.py
sisu/pit/__init__.py
sisu/pit/building_summary.py
sisu/pit/gismo_wrapper.py
sisu/pit/hierarchical_functions.py
sisu/pit/lcs.py
sisu/pit/measures.py
sisu/pit/structure_from_wiki.py
sisu/pit/visualizer.py
sisu/pit/covid/__init__.py
sisu/pit/covid/data_loader.py
sisu/pit/preprocessing/__init__.py
sisu/pit/preprocessing/covid19.py
sisu/pit/preprocessing/sentences.py
sisu/pit/preprocessing/tokenizer.py
sisu/preprocessing/__init__.py
sisu/preprocessing/language.py
sisu/preprocessing/tokenizer.py
tests/__init__.py
tests/test_sisu.py
sisu-0.2.0.dist-info/AUTHORS.rst
sisu-0.2.0.dist-info/LICENSE
sisu-0.2.0.dist-info/METADATA
sisu-0.2.0.dist-info/WHEEL
sisu-0.2.0.dist-info/top_level.txt
sisu-0.2.0.dist-info/RECORD
