Metadata-Version: 2.1
Name: sisu
Version: 0.2.0
Summary: Performs extractive, hierarchical, summarization out of a corpus of documents.
Home-page: https://github.com/balouf/sisu
Author: Mélanie Cambus, Marc-Olivier Buob, Fabien Mathieu
Author-email: fabien.mathieu@normalesup.org
License: BSD license
Keywords: sisu
Platform: UNKNOWN
Classifier: Development Status :: 2 - Pre-Alpha
Classifier: Intended Audience :: Developers
Classifier: License :: OSI Approved :: BSD License
Classifier: Natural Language :: English
Classifier: Programming Language :: Python :: 3
Classifier: Programming Language :: Python :: 3.6
Classifier: Programming Language :: Python :: 3.7
Classifier: Programming Language :: Python :: 3.8
Requires-Python: >=3.6
Requires-Dist: nltk
Requires-Dist: numpy
Requires-Dist: dill
Requires-Dist: gismo
Requires-Dist: scikit-network
Requires-Dist: matplotlib
Requires-Dist: PyQt5
